{
    "$schema": "https://schema.management.azure.com/schemas/2019-04-01/deploymentTemplate.json#",
    "contentVersion": "1.0.0.0",
    "resources": [
        {
            "name": "cloudynademo6",
            "type": "Microsoft.Storage/storageAccounts",
            "apiVersion": "2019-04-01",
            "sku": {
                "name": "Standard_LRS"
            },
            "tags": {
                "conference": "Cloudyna2019"
            },
            "kind": "Storage",
            "location": "westeurope"
        }
    ]
}